[
  {
    "priority": "P0",
    "title": "JWT_SECRET environment variable not set in production",
    "steps": [
      "Navigate to https://2ndshift.vercel.app/login",
      "Enter valid credentials",
      "Click Sign in"
    ],
    "expected": "User logs in successfully and is redirected to dashboard",
    "actual": "Error: JWT_SECRET environment variable is not set in production. Please set JWT_SECRET in Vercel dashboard (Settings > Environment Variables). Generate a secret: openssl rand -base64 32",
    "screenshot": null,
    "logs": [
      "Error: JWT_SECRET environment variable is not set in production",
      "Stack trace shows error in lib/auth/jwt.ts at generateAccessToken"
    ],
    "suggested_fix": "Set JWT_SECRET and REFRESH_SECRET environment variables in Vercel Dashboard → Settings → Environment Variables. Generate secrets using: openssl rand -base64 32 (run twice for two different secrets). Redeploy application after setting variables."
  },
  {
    "priority": "P0",
    "title": "Client and Worker unable to login",
    "steps": [
      "Navigate to login page",
      "Enter credentials for worker or client",
      "Click Sign in"
    ],
    "expected": "Successful login and redirect to appropriate dashboard",
    "actual": "Login fails with JWT_SECRET error",
    "screenshot": null,
    "logs": [
      "JWT_SECRET environment variable is not set in production"
    ],
    "suggested_fix": "Same as above - set JWT_SECRET and REFRESH_SECRET in Vercel. This is blocking all authentication."
  }
]
